Metadata-Version: 2.1
Name: nith-results
Version: 0.0.1
Summary: A Script to display results of nith
Home-page: http://github.com/srbcheema1/nith_results
Author: Sarbjit Singh
Author-email: srbcheema1@gmail.com
License: MIT License
Platform: UNKNOWN
Classifier: Operating System :: POSIX :: Linux
Classifier: License :: OSI Approved :: MIT License
Classifier: Programming Language :: Python :: 3.5
